nightowl/__init__.py
nightowl/base.py
nightowl/config.py
nightowl/helper.py
nightowl/mixins.py
nightowl/exceptions/__init__.py
nightowl/exceptions/base.py
nightowl/exceptions/db.py
nightowl-0.2.0.dist-info/licenses/LICENSE
nightowl-0.2.0.dist-info/METADATA
nightowl-0.2.0.dist-info/WHEEL
nightowl-0.2.0.dist-info/top_level.txt
nightowl-0.2.0.dist-info/RECORD
