Metadata-Version: 2.4
Name: nightowl
Version: 0.2.0
Summary: Base metrics and monitoring utilities for consistent Prometheus monitoring across services
License: MIT
Requires-Python: >=3.11
License-File: LICENSE
Requires-Dist: fastapi>=0.104.1
Requires-Dist: prometheus-client>=0.23.1
Dynamic: license-file
